aws_target_discovery/__init__.py
aws_target_discovery/main.py
aws_target_discovery-0.3.0.dist-info/METADATA
aws_target_discovery-0.3.0.dist-info/RECORD
aws_target_discovery-0.3.0.dist-info/WHEEL
aws_target_discovery-0.3.0.dist-info/entry_points.txt
aws_target_discovery-0.3.0.dist-info/top_level.txt
